[
  {
    "id":"0",
    "key":"aKey",
    "category":"aCategory",
    "description":"aDescription",
    "name":"Invoice-EN",
    "version":42,
    "resource":"aResourceName",
    "deploymentId":"aDeploymentId",
    "diagram":"aResourceName",
    "suspended":true
  },
  {
    "id":"1",
    "key":"aKey",
    "category":"aCategory",
    "description":"aDescription",
    "name":"Invoice-DE",
    "version":42,
    "resource":"aResourceName",
    "deploymentId":"aDeploymentId",
    "diagram":"aResourceName",
    "suspended":true
  },
  {
    "id":"2",
    "key":"aKey",
    "category":"aCategory",
    "description":"aDescription",
    "name":"Delivery-Manager-EN",
    "version":42,
    "resource":"aResourceName",
    "deploymentId":"aDeploymentId",
    "diagram":"aResourceName",
    "suspended":true
  },
  {
    "id":"3",
    "key":"aKey",
    "category":"aCategory",
    "description":"aDescription",
    "name":"Delivery-Manager-DE",
    "version":42,
    "resource":"aResourceName",
    "deploymentId":"aDeploymentId",
    "diagram":"aResourceName",
    "suspended":true
  },
  {
    "id":"4",
    "key":"aKey",
    "category":"aCategory",
    "description":"aDescription",
    "name":"aName",
    "version":42,
    "resource":"aResourceName",
    "deploymentId":"aDeploymentId",
    "diagram":"aResourceName",
    "suspended":true
  },
  {
    "id":"5",
    "key":"aKey",
    "category":"aCategory",
    "description":"aDescription",
    "name":"aName",
    "version":42,
    "resource":"aResourceName",
    "deploymentId":"aDeploymentId",
    "diagram":"aResourceName",
    "suspended":true
  },
  {
    "id":"6",
    "key":"aKey",
    "category":"aCategory",
    "description":"aDescription",
    "name":"aName",
    "version":42,
    "resource":"aResourceName",
    "deploymentId":"aDeploymentId",
    "diagram":"aResourceName",
    "suspended":true
  },
  {
    "id":"7",
    "key":"aKey",
    "category":"aCategory",
    "description":"aDescription",
    "name":"aName",
    "version":42,
    "resource":"aResourceName",
    "deploymentId":"aDeploymentId",
    "diagram":"aResourceName",
    "suspended":true
  },
  {
    "id":"8",
    "key":"aKey",
    "category":"aCategory",
    "description":"aDescription",
    "name":"aName",
    "version":42,
    "resource":"aResourceName",
    "deploymentId":"aDeploymentId",
    "diagram":"aResourceName",
    "suspended":true
  },
  {
    "id":"9",
    "key":"aKey",
    "category":"aCategory",
    "description":"aDescription",
    "name":"aName",
    "version":42,
    "resource":"aResourceName",
    "deploymentId":"aDeploymentId",
    "diagram":"aResourceName",
    "suspended":true
  }
]